dane_server/RabbitMQListener.py
dane_server/RabbitMQPublisher.py
dane_server/__init__.py
dane_server/api.py
dane_server/handler.py
dane_server/server.py
dane_server/web/index.html
dane_server/web/js/index.js
dane_server-0.3.1.dist-info/METADATA
dane_server-0.3.1.dist-info/WHEEL
dane_server-0.3.1.dist-info/LICENSE
dane_server-0.3.1.dist-info/RECORD
