Metadata-Version: 2.1
Name: dane-server
Version: 0.3.1
Summary: Back-end for the Distributed Annotation 'n' Enrichment (DANE) system
Home-page: https://github.com/CLARIAH/DANE
License: Apache-2.0
Author: Nanne van Noord
Author-email: n.j.e.vannoord@uva.nl
Requires-Python: >=3.10,<4.0
Classifier: Development Status :: 4 - Beta
Classifier: Intended Audience :: Developers
Classifier: Intended Audience :: Science/Research
Classifier: License :: OSI Approved :: Apache Software License
Classifier: Programming Language :: Python :: 3
Classifier: Programming Language :: Python :: 3.10
Classifier: Programming Language :: Python :: 3.11
Classifier: Programming Language :: Python :: 3
Requires-Dist: dane (>=0.3.6,<0.4.0)
Requires-Dist: elasticsearch7
Requires-Dist: flask (>=2.1.0,<2.2.0)
Requires-Dist: flask-restx
Requires-Dist: pika
Requires-Dist: requests
Requires-Dist: werkzeug (<2.2.0)
Project-URL: Repository, https://github.com/CLARIAH/DANE
